lambda_analyzer/__init__.py
lambda_analyzer/cli/__init__.py
lambda_analyzer/cli/interactive.py
lambda_analyzer/cli/main.py
lambda_analyzer/cli/commands/__init__.py
lambda_analyzer/cli/commands/analyze.py
lambda_analyzer/cli/commands/generate.py
lambda_analyzer/cli/commands/security.py
lambda_analyzer/config/__init__.py
lambda_analyzer/config/default.yaml
lambda_analyzer/core/__init__.py
lambda_analyzer/core/analyzer.py
lambda_analyzer/core/ast_parser.py
lambda_analyzer/core/policy_generator.py
lambda_analyzer/core/service_detector.py
lambda_analyzer/templates/__init__.py
lambda_analyzer/templates/cloudformation.py
lambda_analyzer/templates/sam.py
lambda_analyzer/utils/__init__.py
lambda_analyzer/utils/aws_mappings.py
lambda_analyzer/utils/patterns.py
lambda_analyzer/utils/security.py
tests/__init__.py
tests/conftest.py
tests/fixtures/__init__.py
tests/fixtures/insecure_lambda.py
tests/fixtures/multi_service_lambda.py
tests/fixtures/s3_lambda.py
tests/fixtures/simple_lambda.py
tests/unit/__init__.py
tests/unit/test_analyzer.py
tests/unit/test_ast_parser.py
tests/unit/test_service_detector.py
lambda_analyzer-1.0.1.dist-info/METADATA
lambda_analyzer-1.0.1.dist-info/WHEEL
lambda_analyzer-1.0.1.dist-info/entry_points.txt
lambda_analyzer-1.0.1.dist-info/top_level.txt
lambda_analyzer-1.0.1.dist-info/RECORD
